odoo/addons/hr_attendance_rfid/README.rst
odoo/addons/hr_attendance_rfid/__init__.py
odoo/addons/hr_attendance_rfid/__manifest__.py
odoo/addons/hr_attendance_rfid/data/ir_rule.xml
odoo/addons/hr_attendance_rfid/i18n/es.po
odoo/addons/hr_attendance_rfid/i18n/es_ES.po
odoo/addons/hr_attendance_rfid/i18n/fr.po
odoo/addons/hr_attendance_rfid/i18n/hr_attendance_rfid.pot
odoo/addons/hr_attendance_rfid/i18n/it.po
odoo/addons/hr_attendance_rfid/migrations/14.0.1.0.0/post-migration.py
odoo/addons/hr_attendance_rfid/models/__init__.py
odoo/addons/hr_attendance_rfid/models/hr_employee.py
odoo/addons/hr_attendance_rfid/readme/CONFIGURE.rst
odoo/addons/hr_attendance_rfid/readme/CONTRIBUTORS.rst
odoo/addons/hr_attendance_rfid/readme/DESCRIPTION.rst
odoo/addons/hr_attendance_rfid/readme/USAGE.rst
odoo/addons/hr_attendance_rfid/security/hr_attendance_rfid.xml
odoo/addons/hr_attendance_rfid/security/ir.model.access.csv
odoo/addons/hr_attendance_rfid/static/description/icon.png
odoo/addons/hr_attendance_rfid/static/description/index.html
odoo/addons/hr_attendance_rfid/tests/__init__.py
odoo/addons/hr_attendance_rfid/tests/test_hr_attendance_rfid_process.py
odoo/addons/hr_attendance_rfid/views/hr_employee_view.xml
odoo14_addon_hr_attendance_rfid-14.0.1.1.3.dist-info/METADATA
odoo14_addon_hr_attendance_rfid-14.0.1.1.3.dist-info/WHEEL
odoo14_addon_hr_attendance_rfid-14.0.1.1.3.dist-info/top_level.txt
odoo14_addon_hr_attendance_rfid-14.0.1.1.3.dist-info/RECORD
